[
  {
    "types": "color",
    "name": "black",
    "colors": [
      "#000000",
      "#111111",
      "#222222",
      "#1a1a1a",
      "#333333",
      "#444444",
      "#4d4d4d",
      "#666666",
      "#777777",
      "#808080",
      "#999999",
      "#b3b3b3",
      "#cccccc",
      "#e6e6e6",
      "#e8e8e8",
      "#ffffff"
    ]
  },
  {
    "types": "color",
    "name": "Grey",
    "colors": [
      "#404040",
      "#4d4d4d",
      "#5a5a5a",
      "#6a6a6a",
      "#666666",
      "#737373",
      "#808080",
      "#8d8d8d",
      "#999999",
      "#a6a6a6",
      "#b3b3b3",
      "#c0c0c0",
      "#cccccc",
      "#d9d9d9",
      "#e6e6e6",
      "#f2f2f2"
    ]
  },
  {
    "types": "color",
    "name": "White",
    "colors": [
      "#7b7b7b",
      "#939393",
      "#acacac",
      "#c4c4c4",
      "#dddddd",
      "#f5f5f5",
      "#f6f6f6",
      "#f7f7f7",
      "#f8f8f8",
      "#f9f9f9",
      "#fafafa",
      "#fbfbfb",
      "#fcfcfc",
      "#fdfdfd",
      "#fefefe",
      "#ffffff"
    ]
  },
  {
    "types": "color",
    "name": "Red",
    "colors": [
      "#660000",
      "#800000",
      "#990000",
      "#b30000",
      "#cc0000",
      "#e60000",
      "#ff0000",
      "#ff1a1a",
      "#ff3333",
      "#ff4d4d",
      "#ff6666",
      "#ff8080",
      "#ff9999",
      "#ffb3b3",
      "#ffcccc",
      "#ffe6e6"
    ]
  },
  {
    "types": "color",
    "name": "Yellow",
    "colors": [
      "#808000",
      "#999900",
      "#b3b300",
      "#cccc00",
      "#e6e600",
      "#ffff00",
      "#ffff00",
      "#ffff1a",
      "#ffff33",
      "#ffff4d",
      "#ffff66",
      "#ffff80",
      "#ffff99",
      "#ffffb3",
      "#ffffcc",
      "#ffffe6"
    ]
  },
  {
    "types": "color",
    "name": "Orange",
    "colors": [
      "#664200",
      "#805300",
      "#996300",
      "#b37300",
      "#cc8400",
      "#e69500",
      "#ffa500",
      "#ffae1a",
      "#ffb733",
      "#ffc04d",
      "#ffc966",
      "#ffd280",
      "#ffdb99",
      "#ffe4b3",
      "#ffedcc",
      "#fff6e6"
    ]
  },
  {
    "types": "color",
    "name": "Blue",
    "colors": [
      "#006666",
      "#008080",
      "#009999",
      "#00b3b3",
      "#00cccc",
      "#00e6e6",
      "#00ffff",
      "#1affff",
      "#33ffff",
      "#4dffff",
      "#66ffff",
      "#80ffff",
      "#99ffff",
      "#b3ffff",
      "#ccffff",
      "#e6ffff"
    ]
  },
  {
    "types": "color",
    "name": "Dark Blue",
    "colors": [
      "#000066",
      "#000080",
      "#000099",
      "#0000b3",
      "#0000cc",
      "#0000e6",
      "#0000ff",
      "#1a1aff",
      "#3333ff",
      "#4d4dff",
      "#6666ff",
      "#8080ff",
      "#9999ff",
      "#b3b3ff",
      "#ccccff",
      "#e6e6ff"
    ]
  },
  {
    "types": "color",
    "name": "Navy",
    "colors": [
      "#000033",
      "#000040",
      "#00004d",
      "#00005a",
      "#000066",
      "#000073",
      "#000080",
      "#1a1a8d",
      "#333399",
      "#4d4da6",
      "#6666b3",
      "#8080c0",
      "#9999cc",
      "#b3b3d9",
      "#cccce6",
      "#e6e6f2"
    ]
  },
  {
    "types": "color",
    "name": "Teal",
    "colors": [
      "#003333",
      "#004040",
      "#004d4d",
      "#005a5a",
      "#006666",
      "#007373",
      "#008080",
      "#1a8d8d",
      "#339999",
      "#4da6a6",
      "#66b3b3",
      "#80c0c0",
      "#99cccc",
      "#b3d9d9",
      "#cce6e6",
      "#e6f2f2"
    ]
  },
  {
    "types": "color",
    "name": "Green",
    "colors": [
      "#006600",
      "#008000",
      "#009900",
      "#00b300",
      "#00cc00",
      "#00e600",
      "#00ff00",
      "#1aff1a",
      "#33ff33",
      "#4dff4d",
      "#66ff66",
      "#80ff80",
      "#99ff99",
      "#b3ffb3",
      "#ccffcc",
      "#e6ffe6"
    ]
  },
  {
    "types": "color",
    "name": "Pink",
    "colors": [
      "#660066",
      "#800080",
      "#990099",
      "#b300b3",
      "#cc00cc",
      "#e600e6",
      "#ff00ff",
      "#ff1aff",
      "#ff33ff",
      "#ff4dff",
      "#ff66ff",
      "#ff80ff",
      "#ff99ff",
      "#ffb3ff",
      "#ffccff",
      "#ffe6ff"
    ]
  },
  {
    "types": "color",
    "name": "Purple",
    "colors": [
      "#330033",
      "#400040",
      "#4d004d",
      "#5a005a",
      "#660066",
      "#730073",
      "#800080",
      "#8d1a8d",
      "#993399",
      "#a64da6",
      "#b366b3",
      "#c080c0",
      "#cc99cc",
      "#d9b3d9",
      "#e6cce6",
      "#f2e6f2"
    ]
  },
  {
    "types": "color",
    "name": "Maroon",
    "colors": [
      "#330000",
      "#400000",
      "#4d0000",
      "#5a0000",
      "#660000",
      "#730000",
      "#800000",
      "#8d1a1a",
      "#993333",
      "#a64d4d",
      "#b36666",
      "#c08080",
      "#cc9999",
      "#d9b3b3",
      "#e6cccc",
      "#f2e6e6"
    ]
  },
  {
    "types": "special",
    "name": "Special Color",
    "colors": [
      "#E2b8ac",
      "#919f88",
      "#cedadb",
      "#98a7ae",
      "#f9f3e7",
      "#e5dccd",
      "#f0bfb1",
      "#8d9e96",
      "#5e887c",
      "#1d4e55",
      "#f1af9b",
      "#f5d1c3",
      "#efc98d",
      "#aab8bb",
      "#c4d7d1",
      "#8ec4c4",
      "#ea9185",
      "#9693cb",
      "#d997ae",
      "#bcd8ec",
      "#acae8c",
      "#e8d2a1",
      "#bc9376",
      "#d1a78d",
      "#e9a379",
      "#eac47e",
      "#f7f8f3",
      "#f2f1ef",
      "#e2d8d6",
      "#d5d7d6",
      "#f0efed",
      "#e3cbb3",
      "#a99f9e",
      "#7c95b4",
      "#c799b6",
      "#d6b89a",
      "#9fbecb",
      "#457963",
      "#c28f93",
      "#a88888"
    ]
  }
]
